actions/__init__.py
careers/__init__.py
careers/actions.py
careers/cli.py
careers/database.py
careers/skeleton.py
careers/util.py
consultor/__init__.py
consultor/cli.py
consultor-0.1.6.dist-info/DESCRIPTION.rst
consultor-0.1.6.dist-info/METADATA
consultor-0.1.6.dist-info/RECORD
consultor-0.1.6.dist-info/WHEEL
consultor-0.1.6.dist-info/entry_points.txt
consultor-0.1.6.dist-info/metadata.json
consultor-0.1.6.dist-info/top_level.txt
database/__init__.py
util/__init__.py
