Metadata-Version: 2.0
Name: consultor
Version: 0.1.6
Summary: Consultor te ayuda a explorar las diferentes carreras y cursos que las universidades ofrecen
Home-page: http://...
Author: Kevin Eduardo
Author-email: rgkevin.lopez@gmail.com
License: mit
Platform: any
Classifier: Development Status :: 4 - Beta
Classifier: Programming Language :: Python
Requires-Dist: beautifultable
Requires-Dist: pre-commit
Requires-Dist: pymongo
